{
  "coord": {
    "lon": 121.5319,
    "lat": 25.0478
  },
  "weather": [
    {
      "id": 501,
      "main": "Rain",
      "description": "中雨",
      "icon": "10d"
    }
  ],
  "base": "stations",
  "main": {
    "temp": 27.05,
    "feels_like": 28.22,
    "temp_min": 26.62,
    "temp_max": 27.96,
    "pressure": 1000,
    "humidity": 61,
    "sea_level": 1000,
    "grnd_level": 981
  },
  "visibility": 10000,
  "wind": {
    "speed": 3.09,
    "deg": 100
  },
  "rain": {
    "1h": 2.05
  },
  "clouds": {
    "all": 75
  },
  "dt": 1752042911,
  "sys": {
    "type": 2,
    "id": 266033,
    "country": "TW",
    "sunrise": 1752009026,
    "sunset": 1752058036
  },
  "timezone": 28800,
  "id": 1668341,
  "name": "Taipei",
  "cod": 200,
  "updated_at": "2025-07-09 14:35:10"
}
