{
  "coord": {
    "lon": 121.5319,
    "lat": 25.0478
  },
  "weather": [
    {
      "id": 520,
      "main": "Rain",
      "description": "陣雨",
      "icon": "09n"
    }
  ],
  "base": "stations",
  "main": {
    "temp": 28.4,
    "feels_like": 29.81,
    "temp_min": 27.8,
    "temp_max": 29.39,
    "pressure": 995,
    "humidity": 58,
    "sea_level": 995,
    "grnd_level": 976
  },
  "visibility": 10000,
  "wind": {
    "speed": 8.75,
    "deg": 90
  },
  "rain": {
    "1h": 2.05
  },
  "clouds": {
    "all": 75
  },
  "dt": 1752870953,
  "sys": {
    "type": 2,
    "id": 266033,
    "country": "TW",
    "sunrise": 1752873294,
    "sunset": 1752921901
  },
  "timezone": 28800,
  "id": 1668341,
  "name": "Taipei",
  "cod": 200,
  "updated_at": "2025-07-19 04:40:29"
}
