{
  "coord": {
    "lon": 121.5319,
    "lat": 25.0478
  },
  "weather": [
    {
      "id": 804,
      "main": "Clouds",
      "description": "陰，多雲",
      "icon": "04n"
    }
  ],
  "base": "stations",
  "main": {
    "temp": 27.76,
    "feels_like": 30.83,
    "temp_min": 27.25,
    "temp_max": 27.82,
    "pressure": 1003,
    "humidity": 75,
    "sea_level": 1003,
    "grnd_level": 986
  },
  "visibility": 10000,
  "wind": {
    "speed": 0.45,
    "deg": 150,
    "gust": 3.13
  },
  "clouds": {
    "all": 99
  },
  "dt": 1749402510,
  "sys": {
    "type": 2,
    "id": 266033,
    "country": "TW",
    "sunrise": 1749416613,
    "sunset": 1749465771
  },
  "timezone": 28800,
  "id": 1668341,
  "name": "Taipei",
  "cod": 200,
  "updated_at": "2025-06-09 01:08:32"
}
