{
  "coord": {
    "lon": 121.5319,
    "lat": 25.0478
  },
  "weather": [
    {
      "id": 803,
      "main": "Clouds",
      "description": "多雲",
      "icon": "04n"
    }
  ],
  "base": "stations",
  "main": {
    "temp": 29.07,
    "feels_like": 33.46,
    "temp_min": 27.82,
    "temp_max": 29.95,
    "pressure": 1004,
    "humidity": 73,
    "sea_level": 1004,
    "grnd_level": 986
  },
  "visibility": 10000,
  "wind": {
    "speed": 2.57,
    "deg": 100
  },
  "clouds": {
    "all": 75
  },
  "dt": 1749382058,
  "sys": {
    "type": 2,
    "id": 266033,
    "country": "TW",
    "sunrise": 1749330213,
    "sunset": 1749379348
  },
  "timezone": 28800,
  "id": 1668341,
  "name": "Taipei",
  "cod": 200,
  "updated_at": "2025-06-08 19:27:56"
}
