{
  "coord": {
    "lon": 121.5319,
    "lat": 25.0478
  },
  "weather": [
    {
      "id": 520,
      "main": "Rain",
      "description": "陣雨",
      "icon": "09d"
    }
  ],
  "base": "stations",
  "main": {
    "temp": 26.32,
    "feels_like": 26.32,
    "temp_min": 25.93,
    "temp_max": 27.96,
    "pressure": 1004,
    "humidity": 89,
    "sea_level": 1004,
    "grnd_level": 986
  },
  "visibility": 10000,
  "wind": {
    "speed": 4.63,
    "deg": 90
  },
  "rain": {
    "1h": 3.26
  },
  "clouds": {
    "all": 75
  },
  "dt": 1749708379,
  "sys": {
    "type": 2,
    "id": 266033,
    "country": "TW",
    "sunrise": 1749675816,
    "sunset": 1749725035
  },
  "timezone": 28800,
  "id": 1668341,
  "name": "Taipei",
  "cod": 200,
  "updated_at": "2025-06-12 14:13:13"
}
