{
  "coord": {
    "lon": 121.5319,
    "lat": 25.0478
  },
  "weather": [
    {
      "id": 801,
      "main": "Clouds",
      "description": "晴，少雲",
      "icon": "02d"
    }
  ],
  "base": "stations",
  "main": {
    "temp": 29.49,
    "feels_like": 29.55,
    "temp_min": 28.91,
    "temp_max": 30.04,
    "pressure": 1009,
    "humidity": 44,
    "sea_level": 1009,
    "grnd_level": 991
  },
  "visibility": 10000,
  "wind": {
    "speed": 4.63,
    "deg": 80
  },
  "clouds": {
    "all": 20
  },
  "dt": 1755387045,
  "sys": {
    "type": 2,
    "id": 266033,
    "country": "TW",
    "sunrise": 1755379719,
    "sunset": 1755426459
  },
  "timezone": 28800,
  "id": 1668341,
  "name": "Taipei",
  "cod": 200,
  "updated_at": "2025-08-17 07:30:45"
}
