{
  "coord": {
    "lon": 121.5319,
    "lat": 25.0478
  },
  "weather": [
    {
      "id": 800,
      "main": "Clear",
      "description": "晴",
      "icon": "01n"
    }
  ],
  "base": "stations",
  "main": {
    "temp": 23.5,
    "feels_like": 23.94,
    "temp_min": 23.28,
    "temp_max": 24.47,
    "pressure": 1011,
    "humidity": 78,
    "sea_level": 1011,
    "grnd_level": 992
  },
  "visibility": 10000,
  "wind": {
    "speed": 3.13,
    "deg": 100,
    "gust": 10.28
  },
  "clouds": {
    "all": 0
  },
  "dt": 1748608960,
  "sys": {
    "type": 2,
    "id": 266033,
    "country": "TW",
    "sunrise": 1748552673,
    "sunset": 1748601513
  },
  "timezone": 28800,
  "id": 1668341,
  "name": "Taipei",
  "cod": 200,
  "updated_at": "2025-05-30 20:42:39"
}
