{
  "coord": {
    "lon": 121.5319,
    "lat": 25.0478
  },
  "weather": [
    {
      "id": 803,
      "main": "Clouds",
      "description": "多雲",
      "icon": "04n"
    }
  ],
  "base": "stations",
  "main": {
    "temp": 28.9,
    "feels_like": 30.87,
    "temp_min": 27.8,
    "temp_max": 30.18,
    "pressure": 993,
    "humidity": 60,
    "sea_level": 993,
    "grnd_level": 975
  },
  "visibility": 10000,
  "wind": {
    "speed": 2.57,
    "deg": 290
  },
  "clouds": {
    "all": 75
  },
  "dt": 1753789403,
  "sys": {
    "type": 2,
    "id": 266033,
    "country": "TW",
    "sunrise": 1753737584,
    "sunset": 1753785645
  },
  "timezone": 28800,
  "id": 1668341,
  "name": "Taipei",
  "cod": 200,
  "updated_at": "2025-07-29 19:46:38"
}
